setup.py
puppet/__init__.py
puppet/format.py
puppet/scanner/__init__.py
puppet/scanner/scanner.py
puppet_format.egg-info/PKG-INFO
puppet_format.egg-info/SOURCES.txt
puppet_format.egg-info/dependency_links.txt
puppet_format.egg-info/entry_points.txt
puppet_format.egg-info/top_level.txt
test/test.py