Metadata-Version: 1.0
Name: puppet-format
Version: 0.0.1
Summary: Python Puppet Formatter
Home-page: https://github.com/Cofyc/puppet-format
Author: Yecheng Fu
Author-email: UNKNOWN
License: UNKNOWN
Platform: UNKNOWN
